SimpleTermGraphics/__init__.py
SimpleTermGraphics-1.0.dist-info/DESCRIPTION.rst
SimpleTermGraphics-1.0.dist-info/METADATA
SimpleTermGraphics-1.0.dist-info/RECORD
SimpleTermGraphics-1.0.dist-info/WHEEL
SimpleTermGraphics-1.0.dist-info/metadata.json
SimpleTermGraphics-1.0.dist-info/top_level.txt
