Metadata-Version: 2.0
Name: SimpleTermGraphics
Version: 1.0
Summary: An API for making simple terminal graphics. Only works on Unix based terminals
Home-page: UNKNOWN
Author: SuperKooks
Author-email: superkooks@superkooks.com
License: UNKNOWN
Platform: UNKNOWN
